LICENSE
README.md
progbr.py
setup.py
progbr.egg-info/PKG-INFO
progbr.egg-info/SOURCES.txt
progbr.egg-info/dependency_links.txt
progbr.egg-info/requires.txt
progbr.egg-info/top_level.txt