Metadata-Version: 2.1
Name: progbr
Version: 0.3.3
Summary: Uma biblioteca para facilitar sua jornada em matemática
Author: ['Bidjory']
Author-email: anybosoft@gmail.com
Maintainer: Samuel Bidjory
License: MIT
Classifier: Programming Language :: Python :: 3
Classifier: License :: OSI Approved :: MIT License
Classifier: Operating System :: OS Independent
Requires-Python: >=3.6
License-File: LICENSE
